Workbook

Sheet Respostas ao formulário 1
A1: Carimbo de data/hora | B1: Nome Completo | C1: Quando se formou? | D1: Em que ano você começou a atuar como psicóloga clínica? | E1: Nome do serviço | F1: Valor atual praticado hoje | G1: Formato | H1: Recorrência | I1: Nº de clientes | J1: Receita mensal estimada | K1: Nome do serviço 2 | L1: Valor atual | M1: Formato 2 | N1: Recorrência 2 | O1: Nº de clientes 2 | P1: Receita mensal estimada 2 | Q1: Existe um terceiro serviço, se sim, qual? | R1: Qual serviço representa a maior parte de sua renda atual? | S1: Qual serviço demanda mais energia e tempo de sua parte? | T1: Existe uma dependência significativa de um único serviço para a sustentabilidade de seu negócio? | U1: Faturamento médio dos últimos 2 meses | V1: Maior faturamento nos últimos 6 meses | W1: Menor faturamento nos últimos 6 meses | X1: Receita média mensal previsível (fixa) | Y1: Receita instável (variável) | Z1: Quantos atendimentos você realiza por semana atualmente? | AA1: Se sua agenda estivesse completamente cheia, quantos pacientes você conseguiria sustentar com a mesma qulidade por semana? (capacidade máxima real) | AB1: Quantos dias você trabalha por semana? | AC1: Existe um limite máximo de atendimentos ou dias de trabalho definido por você? | AD1: Se sim, qual é esse limite? (deixe em branco se sua resposta acima foi "Não") | AE1: Valor mínimo cobrado por serviço | AF1: Valor máximo cobrado por serviço | AG1: Valor médio real cobrado | AH1: Quando foi realizado o último reajuste de valores? | AI1: Existe uma regra clara e definida para o reajuste de seus preços? | AJ1: Se sim, qual é essa regra? (deixe em branco se sua resposta acima foi "Não") | AK1: De 0 a 5, teve alguma surpresa em descrever os números aqui? | AL1: Se você pudesse escolher, quais dos seus atuais pacientes você gostaria de atender mais?” | AM1: Na sua percepção, o que faz um paciente escolher você em vez de outro profissional? | AN1: Quantos pacientes novos você recebeu nos últimos 60 dias? | AO1: Como você avalia sua autoridade digital hoje (redes sociais, conteúdo, visibilidade online)? | AP1: Qual é o perfil predominante dos pacientes que você atende atualmente? | AQ1: Com qual perfil de paciente você deseja atuar no futuro? | AR1: Existe algum perfil de cliente que você considera que consome mais sua energia ou que não se identifica? | AS1: Você já passou por alguma mentoria ou consultoria de negócios antes? e sim, o que considerou que funcionou e o que não funcionou? | AT1: Qual é o faturamento realista mensal que você almeja alcançar? | AU1: Quantos atendimentos semanais você deseja realizar? | AV1: Você pretende depender exclusivamente da clínica individual? | AW1: Você deseja ter outros serviços além da clínica individual ou já teve? Se sim, quais? | AX1: Quantos dias por semana você deseja trabalhar? | AY1: Seu modelo de negócio atual o(a) conduz a esses objetivos? | AZ1: Se a resposta for "Não", quais mudanças precisam ser implementadas nos próximos 90 dias para alinhar seu modelo aos seus objetivos? (deixe em branco se respondeu "Sim") | BA1: O que vem a mente para completar a frase: Eu sou uma psicóloga que... | BB1: Nos próximos 2 anos, profissionalmente eu quero ... | BC1: Para isso, preciso ajustar imediatamente...
A2: 46265.562 | B2: Sannara Freitas | C2: 2025 | E2: Psicoterapia | F2: R$ 80,00 a R$ 100,00 por sessão (média de R$ 340,00/mês por paciente) | G2: Online | H2: Mensal | I2: 4 pacientes pagantes (+ 1 atendimento pro bono) | J2: R$ 1.360,00 | R2: Psicoterapia Individual. | S2: Psicoterapia Individual. | T2: Sim, dependência de 100% das sessões individuais. | U2: R$ 1.360,00 | V2: R$ 1.360,00 | W2: R$ 1.360,00 | X2: R$ 1.200 | Z2: 4 | AA2: 16 | AB2: 5 | AC2: Não | AE2: 80 | AF2: 100 | AG2: 85 | AH2: março | AI2: Sim | AJ2: ajuste de 15% anual sobre o valor em março | AK2: 0 | AL2: Indicação de colegas. | AP2: Adolescentes a partir de 12 anos do sexo feminino | AQ2: adolescentes | AR2: homens e sexualidade | AS2: não | AT2: R$6.000,00 | AU2: 15 | AV2: Sim | AW2: desejo. Oficinas, palestras, workshop | AX2: segunda a sexta - 3 pacientes por dia ( | AY2: Não | AZ2: Nova Precificação: Estabelecer o valor padrão de R$ 200,00 por sessão para todos os novos pacientes captados. Captação Ativa de Clientes: Implementar uma estratégia constante de posicionamento e atração para alcançar a meta de 9 a 10 pacientes ativos no novo valor. Diversificação de Serviços: Avaliar a criação de um segundo serviço pontual (como palestras corporativas ou orientações) para gerar caixa e diminuir a dependência 100% exclusiva da clínica individual." | BA2: escuta escuta as dores e acolhe os adolescentes | BB2: autoridade na area da psicologia do desenvolvimento | BC2: autoridade digital e academica, networking e precificação
A3: 46267.547 | B3: Francisca ROSELI de Alcântara Madeiro | C3: 2022 | D3: 2023 | E3: Psicoterapia | F3: Varia entre R$ 50,00 e R$ 200,00 particular (plano de saúde são outros valores) | G3: Presencial e Online | H3: Único | I3: Plano acabei de encerrar ou encaminhar 7; mantendo 7 do plano (a decidir continuidade em setembro/outubro); 9 particulares (4 semanal, 4 quinzenal e 1 mensal) | J3: Muito variável - Plano ultimo mes foi R$ 1.416,00; Particulares Último mês foi R$ 1.770,00, julho foi R$ 2.920; e teve mês que chegou a passar de R$ 3.000). Como estou num período de transição e decisão sobre o retorno ao meu vínculo, não tenho recebido novos pacientes de plano já tem um tempo e também não tem colocado energia nos particulares - por conta dessa indefinição. | K3: nao | L3: nao | M3: Presencial | N3: Único | O3: nao | P3: nao | Q3: nao | R3: Psicoterapia | S3: Psicoterapia - atendimento por plano de saúde | T3: sim | U3: Média: R$ 3.740,00 // R$ 3.186 ago; R$ 4.294,00 set | V3: R$ 5.006 (particular e plano de saúde) | W3: R$ 3.186,00 | X3: nao sei informar | Y3: nao sei informar | Z3: varia, pois tenho pacientes quinzenais e mensais - média de 12 pelo menos | AA3: 24 | AB3: 5 | AC3: Sim | AD3: Procuro agendar os atendimentos de segunda à quinta, mas tenho pacientes que só podem na sexta, e tamb´me, na sexta coloco remarcação; Por dia, considerando atendimentos por plano, atendo no maximo 10, sem plano, no máximo 7 | AE3: R$ 50,00 | AF3: R$ 200,00 | AG3: R$ 100,00 (tenho pacientes com valores muito variados) | AH3: Nunca houve reajuste | AI3: Não | AJ3: nao | AK3: 0 | AL3: Mulheres em processos de mudanças/transições diversas (fisicas, emocionais, etc) | AM3: Identificação ou indicação | AN3: 3 do plano | AO3: 3 | AP3: Mulheres | AQ3: Mulheres em processos de transições/mudanças | AR3: clientes que não levam conteúdo/demandas para a clínica | AS3: já, mas em um formato diferente, me ajudou a visualizar algumas coisas em todo o processo que envolve a clínica | AT3: R$ 10.000,00 | AU3: 16 | AV3: Não | AW3: Sim (ja tive grupo de cuidado emocional para gestantes e grupo para mulheres, antes da conclusao do curso de psicologia) | AX3: 4 | AY3: Não | AZ3: Verificar novas formas de captação de pacientes | BA3: Eu sou uma psicóloga que acolhe mulheres em momentos de mudanças e transições, oferecendo um espaço de escuta, presença e cuidado para que elas possam se reconectar consigo mesmas e construir caminhos mais autênticos. | BB3: Nos próximos 2 anos, profissionalmente eu quero consolidar minha clínica e minha atuação como psicóloga, ampliar minha visibilidade e alcançar uma estabilidade financeira que me permita viver da psicologia com autonomia, propósito e qualidade de vida, construindo um negócio que tenha a minha identidade. | BC3: Para isso, preciso ajustar imediatamente minha estratégia de captação de pacientes e a gestão da clínica, transformando o que hoje funciona de forma mais intuitiva em um negócio estruturado, sustentável e alinhado à profissional que quero me tornar.
A4: 46267.244 | B4: Marissa Lima | C4: 2017 | D4: 2017 | E4: Psicoterapia | F4: 150 | G4: Presencial | H4: Mensal | I4: 10 | J4: 4000 | K4: Supervisão | L4: 200 | M4: Online | N4: Mensal | O4: 9 | P4: 1600 | Q4: Sim, café com Rogers | R4: Psicoterapia | S4: Psicoterapia | T4: Sim, pois a psicoterapia é a maior parte da renda | U4: 6000 | V4: 9000 | W4: 6000 | X4: 7360 | Y4: 0 | Z4: 10 | AA4: 14 | AB4: 4 | AC4: Sim | AD4: Atendo de segunda a sexta, limite de 4 paciente dia mesclando com supervisão | AE4: 110 | AF4: 150 | AG4: 141 | AH4: Inicio do ano | AI4: Sim | AJ4: Reajuste anual | AK4: 4 | AL4: Com todos | AM4: Confiança, segurança, indicação, autenticidade | AN4: Nenhum | AO4: 3 | AP4: Adolescente | AQ4: Criança, adolescente, pasias | AR4: Não. Quando acontece não é pq não gosto, mas pq sinto que é difícil | AS4: Não. Estava esperando por essa | AT4: 12k | AU4: 14 | AV4: Não | AW4: Sim, já tenho. Supervisão, Café com Rogers, minicurso e quero ter a imersão e formação | AX4: 4 | AY4: Sim | AZ4: Ter ação para cumprir os planejamentos | BA4: Acolhe, escuta, vou no tempo do cliente e promovo transformação na vida das pessoas que acompanho | BB4: Uma clínica sustentável, que eu possa cada vez mais indicar paciente, ser referência na temática do Abuso sexual e ACP, ser palestrante pelo brasil | BC4: Meu comprometimento em seguir o plano de ação certinho, me expor nas redes sociais nos vídeos e no diálogo com profissionais. Continuar acreditando e alimentando o meu valor pessoal. E quero seguir fazendo mentoria vitalícia pra quando chegar na meta, duplicar a meta.

Sheet Respostas_Brutas
A1: Carimbo de data/hora | B1: Nome Completo | C1: Quando se formou? | D1: Em que ano você começou a atuar como psicóloga clínica? | E1: Nome do serviço | F1: Valor atual | G1: Formato | H1: Recorrência | I1: Nº de clientes | J1: Receita mensal estimada | K1: Nome do serviço 2 | L1: Valor atual 2 | M1: Formato 2 | N1: Recorrência 2 | O1: Nº de clientes 2 | P1: Receita mensal estimada 2 | Q1: Qual serviço representa a maior parte de sua renda atual? | R1: Qual serviço demanda mais energia e tempo de sua parte? | S1: Existe uma dependência significativa de um único serviço para a sustentabilidade de seu negócio? | T1: Faturamento médio dos últimos 2 meses | U1: Maior faturamento nos últimos 6 meses | V1: Menor faturamento nos últimos 6 meses | W1: Receita média mensal previsível (fixa) | X1: Receita instável (variável) | Y1: Quantos atendimentos você realiza por semana atualmente? | Z1: Se sua agenda estivesse completamente cheia, quantos pacientes você conseguiria sustentar com a mesma qulidade por semana? (capacidade máxima real) | AA1: Quantos dias você trabalha por semana? | AB1: Existe um limite máximo de atendimentos ou dias de trabalho definido por você? | AC1: Se sim, qual é esse limite? (deixe em branco se sua resposta acima foi "Não") | AD1: Valor mínimo cobrado por serviço | AE1: Valor máximo cobrado por serviço | AF1: Valor médio real cobrado | AG1: Quando foi realizado o último reajuste de valores? | AH1: Existe uma regra clara e definida para o reajuste de seus preços? | AI1: Se sim, qual é essa regra? (deixe em branco se sua resposta acima foi "Não") | AJ1: De 0 a 5, teve alguma surpresa em descrever os números aqui? | AK1: Se você pudesse manter só metade dos seus pacientes atuais, quais ficariam? | AL1: Já identificou qual é o motivo pelo qual seus clientes escolhem o seu atendimento? | AM1: Quantos pacientes novos você recebeu nos últimos 30 dias? | AN1: Como você avalia sua autoridade digital hoje (redes sociais, conteúdo, visibilidade online)? | AO1: Qual é o perfil predominante dos pacientes que você atende atualmente? | AP1: Com qual perfil de paciente você deseja atuar no futuro? | AQ1: Existe algum perfil de cliente que você considera que consome mais sua energia ou que não se identifica? | AR1: Você já passou por alguma mentoria ou consultoria de negócios antes? e sim, o que considerou que funcionou e o que não funcionou? | AS1: Qual é o faturamento realista mensal que você almeja alcançar? | AT1: Quantos atendimentos semanais você deseja realizar? | AU1: Você pretende depender exclusivamente da clínica individual? | AV1: Você deseja ter outros serviços além da clínica individual ou já teve? Se sim, quais? | AW1: Quantos dias por semana você deseja trabalhar? | AX1: Seu modelo de negócio atual o(a) conduz a esses objetivos? | AY1: Se a resposta for "Não", quais mudanças precisam ser implementadas nos próximos 90 dias para alinhar seu modelo aos seus objetivos? (deixe em branco se respondeu "Sim") | AZ1: O que vem a mente para completar a frase: Eu sou uma psicóloga que... | BA1: Nos próximos 2 anos, quero construir... | BB1: Para isso, preciso ajustar imediatamente...
A2: 46265.562 | B2: Sannara Freitas | C2: 2025 | E2: Psicoterapia | F2: R$ 80,00 a R$ 100,00 por sessão (média de R$ 340,00/mês por paciente) | G2: Online | H2: Mensal | I2: 4 pacientes pagantes (+ 1 atendimento pro bono) | J2: R$ 1.360,00 | Q2: Psicoterapia Individual. | R2: Psicoterapia Individual. | S2: Sim, dependência de 100% das sessões individuais. | T2: R$ 1.360,00 | U2: R$ 1.360,00 | V2: R$ 1.360,00 | W2: R$ 1.200 | Y2: 4 | Z2: 16 | AA2: 5 | AB2: Não | AD2: 80 | AE2: 100 | AF2: 85 | AG2: março | AH2: Sim | AI2: ajuste de 15% anual sobre o valor em março | AJ2: 0 | AK2: Indicação de colegas. | AO2: Adolescentes a partir de 12 anos do sexo feminino | AP2: adolescentes | AQ2: homens e sexualidade | AR2: não | AS2: R$6.000,00 | AT2: 15 | AU2: Sim | AV2: desejo. Oficinas, palestras, workshop | AW2: segunda a sexta - 3 pacientes por dia ( | AX2: Não | AY2: Nova Precificação: Estabelecer o valor padrão de R$ 200,00 por sessão para todos os novos pacientes captados. Captação Ativa de Clientes: Implementar uma estratégia constante de posicionamento e atração para alcançar a meta de 9 a 10 pacientes ativos no novo valor. Diversificação de Serviços: Avaliar a criação de um segundo serviço pontual (como palestras corporativas ou orientações) para gerar caixa e diminuir a dependência 100% exclusiva da clínica individual." | AZ2: escuta escuta as dores e acolhe os adolescentes | BA2: autoridade na area da psicologia do desenvolvimento | BB2: autoridade digital e academica, networking e precificação
A3: 46267.244 | B3: Marissa Lima | C3: 2017 | D3: 2017 | E3: Psicoterapia | F3: 150 | G3: Presencial | H3: Mensal | I3: 10 | J3: 4000 | K3: Supervisão | L3: 200 | M3: Online | N3: Mensal | O3: 9 | P3: 1600 | Q3: Sim, café com Rogers | R3: Psicoterapia | S3: Psicoterapia | T3: Sim, pois a psicoterapia é a maior parte da renda | U3: 6000 | V3: 9000 | W3: 6000 | X3: 7360 | Y3: 0 | Z3: 10 | AA3: 14 | AB3: 4 | AC3: Sim | AD3: Atendo de segunda a sexta, limite de 4 paciente dia mesclando com supervisão | AE3: 110 | AF3: 150 | AG3: 141 | AH3: Inicio do ano | AI3: Sim | AJ3: Reajuste anual | AK3: 4 | AL3: Com todos | AM3: Confiança, segurança, indicação, autenticidade | AN3: Nenhum | AO3: 3 | AP3: Adolescente | AQ3: Criança, adolescente, pasias | AR3: Não. Quando acontece não é pq não gosto, mas pq sinto que é difícil | AS3: Não. Estava esperando por essa | AT3: 12k | AU3: 14 | AV3: Não | AW3: Sim, já tenho. Supervisão, Café com Rogers, minicurso e quero ter a imersão e formação | AX3: 4 | AY3: Sim | AZ3: Ter ação para cumprir os planejamentos | BA3: Acolhe, escuta, vou no tempo do cliente e promovo transformação na vida das pessoas que acompanho | BB3: Uma clínica sustentável, que eu possa cada vez mais indicar paciente, ser referência na temática do Abuso sexual e ACP, ser palestrante pelo brasil | BC3: Meu comprometimento em seguir o plano de ação certinho, me expor nas redes sociais nos vídeos e no diálogo com profissionais. Continuar acreditando e alimentando o meu valor pessoal. E quero seguir fazendo mentoria vitalícia pra quando chegar na meta, duplicar a meta.
A4: 46267.547 | B4: Francisca ROSELI de Alcântara Madeiro | C4: 2022 | D4: 2023 | E4: Psicoterapia | F4: Varia entre R$ 50,00 e R$ 200,00 particular (plano de saúde são outros valores) | G4: Presencial e Online | H4: Único | I4: Plano acabei de encerrar ou encaminhar 7; mantendo 7 do plano (a decidir continuidade em setembro/outubro); 9 particulares (4 semanal, 4 quinzenal e 1 mensal) | J4: Muito variável - Plano ultimo mes foi R$ 1.416,00; Particulares Último mês foi R$ 1.770,00, julho foi R$ 2.920; e teve mês que chegou a passar de R$ 3.000). Como estou num período de transição e decisão sobre o retorno ao meu vínculo, não tenho recebido novos pacientes de plano já tem um tempo e também não tem colocado energia nos particulares - por conta dessa indefinição. | K4: nao | L4: nao | M4: Presencial | N4: Único | O4: nao | P4: nao | Q4: nao | R4: Psicoterapia | S4: Psicoterapia - atendimento por plano de saúde | T4: sim | U4: Média: R$ 3.740,00 // R$ 3.186 ago; R$ 4.294,00 set | V4: R$ 5.006 (particular e plano de saúde) | W4: R$ 3.186,00 | X4: nao sei informar | Y4: nao sei informar | Z4: varia, pois tenho pacientes quinzenais e mensais - média de 12 pelo menos | AA4: 24 | AB4: 5 | AC4: Sim | AD4: Procuro agendar os atendimentos de segunda à quinta, mas tenho pacientes que só podem na sexta, e tamb´me, na sexta coloco remarcação; Por dia, considerando atendimentos por plano, atendo no maximo 10, sem plano, no máximo 7 | AE4: R$ 50,00 | AF4: R$ 200,00 | AG4: R$ 100,00 (tenho pacientes com valores muito variados) | AH4: Nunca houve reajuste | AI4: Não | AJ4: nao | AK4: 0 | AL4: Mulheres em processos de mudanças/transições diversas (fisicas, emocionais, etc) | AM4: Identificação ou indicação | AN4: 3 do plano | AO4: 3 | AP4: Mulheres | AQ4: Mulheres em processos de transições/mudanças | AR4: clientes que não levam conteúdo/demandas para a clínica | AS4: já, mas em um formato diferente, me ajudou a visualizar algumas coisas em todo o processo que envolve a clínica | AT4: R$ 10.000,00 | AU4: 16 | AV4: Não | AW4: Sim (ja tive grupo de cuidado emocional para gestantes e grupo para mulheres, antes da conclusao do curso de psicologia) | AX4: 4 | AY4: Não | AZ4: Verificar novas formas de captação de pacientes | BA4: Eu sou uma psicóloga que acolhe mulheres em momentos de mudanças e transições, oferecendo um espaço de escuta, presença e cuidado para que elas possam se reconectar consigo mesmas e construir caminhos mais autênticos. | BB4: Nos próximos 2 anos, profissionalmente eu quero consolidar minha clínica e minha atuação como psicóloga, ampliar minha visibilidade e alcançar uma estabilidade financeira que me permita viver da psicologia com autonomia, propósito e qualidade de vida, construindo um negócio que tenha a minha identidade. | BC4: Para isso, preciso ajustar imediatamente minha estratégia de captação de pacientes e a gestão da clínica, transformando o que hoje funciona de forma mais intuitiva em um negócio estruturado, sustentável e alinhado à profissional que quero me tornar.

Sheet Legenda
A1: Matriz-Mãe v2 — mapeada para o Caderno Diagnóstico real
A3: O que mudou nesta versão:
A4: As fórmulas de Variaveis agora apontam para as 54 colunas reais do seu Forms (Raio-X do Negócio Hoje etc.),
A5: em vez das colunas de exemplo da primeira versão. Ainda usa ARRAYFORMULA — só funciona no Google Sheets.
A7: IMPORTANTE — suposição que fiz e você precisa confirmar:
A8: 'Como você avalia sua autoridade digital hoje?' foi tratada como resposta numérica (1 a 5).
A9: Se no seu Forms essa pergunta for de texto (Baixa/Média/Alta), a variável V9 vai ficar errada — avise para eu corrigir.
A11: Passo a passo para trocar a planilha antiga por esta:
A12: 1. No seu Forms, aba Respostas > menu de três pontinhos > 'Cancelar vínculo do formulário' (desliga da planilha antiga).
A13: 2. Suba este arquivo no Google Drive > abrir com Google Sheets > Arquivo > 'Salvar como Planilhas Google' (vira nativa).
A14: 3. No Forms, clique no ícone verde do Sheets de novo > 'Selecionar planilha existente' > escolha esta planilha nova.
A15: 4. O Forms vai criar a aba de respostas automaticamente aqui dentro. Renomeie essa aba para 'Respostas_Brutas'
... A39: não como número — a fórmula agora limpa o texto (remove 'R$', ajusta separador decimal) antes de calcular.

Sheet Respostas_Brutas_antiga
A1: Carimbo de data/hora | B1: Nome Completo | C1: Quando se formou? | D1: Em que ano você começou a atuar como psicóloga clínica? | E1: Nome do serviço | F1: Valor atual | G1: Formato | H1: Recorrência | I1: Nº de clientes | J1: Receita mensal estimada | K1: Nome do serviço | L1: Valor atual | M1: Formato | N1: Recorrência | O1: Nº de clientes | P1: Receita mensal estimada | Q1: Qual serviço representa a maior parte de sua renda atual? | R1: Qual serviço demanda mais energia e tempo de sua parte? | S1: Existe uma dependência significativa de um único serviço para a sustentabilidade de seu negócio? | T1: Faturamento médio dos últimos 2 meses | U1: Maior faturamento nos últimos 6 meses | V1: Menor faturamento nos últimos 6 meses | W1: Receita média mensal previsível (fixa) | X1: Receita instável (variável) | Y1: Quantos atendimentos você realiza por semana atualmente? | Z1: Capacidade máxima real (agenda completamente cheia) | AA1: Quantos dias você trabalha por semana? | AB1: Existe um limite máximo de atendimentos ou dias definido por você? | AC1: Se sim, qual é esse limite? | AD1: Valor mínimo cobrado por serviço | AE1: Valor máximo cobrado por serviço | AF1: Valor médio real cobrado | AG1: Quando foi realizado o último reajuste de valores? | AH1: Existe uma regra clara e definida para o reajuste de seus preços? | AI1: Se sim, qual é essa regra? | AJ1: De 0 a 5, teve alguma surpresa em descrever os números aqui? | AK1: Se pudesse manter só metade dos pacientes atuais, quais ficariam? | AL1: Já identificou o motivo pelo qual seus clientes escolhem o seu atendimento? | AM1: Quantos pacientes novos você recebeu nos últimos 30 dias? | AN1: Como você avalia sua autoridade digital hoje? | AO1: Qual é o perfil predominante dos pacientes que você atende atualmente? | AP1: Com qual perfil de paciente você deseja atuar no futuro? | AQ1: Existe algum perfil de cliente que consome mais sua energia ou que não se identifica? | AR1: Já passou por mentoria ou consultoria de negócios antes? O que funcionou/não funcionou? | AS1: Qual é o faturamento realista mensal que você almeja alcançar? | AT1: Quantos atendimentos semanais você deseja realizar? | AU1: Pretende depender exclusivamente da clínica individual? | AV1: Deseja ter outros serviços além da clínica individual? Quais? | AW1: Quantos dias por semana você deseja trabalhar? | AX1: Seu modelo de negócio atual conduz a esses objetivos? | AY1: Se 'Não', quais mudanças nos próximos 90 dias? | AZ1: Eu sou uma psicóloga que... | BA1: Nos próximos 2 anos, quero construir... | BB1: Para isso, preciso ajustar imediatamente...
A3: Esta aba é só referência das colunas reais do seu Forms (A até BB) — não precisa preencher nada aqui. A aba de verdade com as respostas é criada pelo próprio Forms quando você vincula.

Sheet Variaveis
A1: Cliente | B1: V1_GapReceita (0-1) | C1: V2_ClientesAtuais (0-1, normalizado /20) | D1: V3_TempoAtuacao (0-1, normalizado /15 anos) | E1: V4_DependeUmServico (0/1) | F1: V5_TaxaOcupacao (0-1) | G1: V6_TemMaisDeUmServico (0/1) | H1: V7_SemRegraReajuste (0/1) | I1: V8_IdentificouDiferencial (0/1) | J1: V9_AutoridadeDigital (0-1, normalizado)
A2: =IF(Respostas_Brutas!B2="","",Respostas_Brutas!B2) -> Sannara Freitas | B2: =IF(Respostas_Brutas!B2="","",IFERROR(IF(IFERROR(VALUE(TRIM(SUBSTITUTE(SUBSTITUTE(SUBSTITUTE(TRIM(Respostas_Brutas!AS2),"R$",""),".",""),",","."))),0)=0,"",(IFERROR(VALUE(TRIM(SUBSTITUTE(SUBSTITUTE(SUBSTITUTE(TRIM(Respostas_Brutas!AS2),"R$",""),".",""),",","."))),0)-IFERROR(VALUE(TRIM(SUBSTITUTE(SUBSTITUTE(SUBSTITUTE(TRIM(Respostas_Brutas!T2),"R$",""),".",""),",","."))),0))/IFERROR(VALUE(TRIM(SUBSTITUTE(SUBSTITUTE(SUBSTITUTE(TRIM(Respostas_Brutas!AS2),"R$",""),".",""),",","."))),0)),"")) | C2: =IF(Respostas_Brutas!B2="","",MIN(1,(IFERROR(VALUE(LEFT(Respostas_Brutas!I2,IFERROR(FIND(" ",Respostas_Brutas!I2)-1,LEN(Respostas_Brutas!I2)))),0)+IFERROR(VALUE(LEFT(Respostas_Brutas!O2,IFERROR(FIND(" ",Respostas_Brutas!O2)-1,LEN(Respostas_Brutas!O2)))),0))/20)) -> 0.2 | D2: =IF(Respostas_Brutas!B2="","",IF(Respostas_Brutas!D2="","",MIN(1,MAX(0,(YEAR(TODAY())-N(Respostas_Brutas!D2))/15)))) | E2: =IF(Respostas_Brutas!B2="","",IF(ISNUMBER(SEARCH("Sim",Respostas_Brutas!S2)),1,0)) -> 1 | F2: =IF(Respostas_Brutas!B2="","",IFERROR(N(Respostas_Brutas!Y2)/N(Respostas_Brutas!Z2),"")) -> 0.25 | G2: =IF(Respostas_Brutas!B2="","",IF(Respostas_Brutas!K2<>"",1,0)) -> 0 | H2: =IF(Respostas_Brutas!B2="","",IF(ISNUMBER(SEARCH("Não",Respostas_Brutas!AH2)),1,0)) -> 0 | I2: =IF(Respostas_Brutas!B2="","",IF(ISNUMBER(SEARCH("Sim",Respostas_Brutas!AL2)),1,0)) -> 0 | J2: =IF(Respostas_Brutas!B2="","",IF(Respostas_Brutas!AN2="","",MIN(1,MAX(0,(N(Respostas_Brutas!AN2)-1)/4))))
A3: =IF(Respostas_Brutas!B3="","",Respostas_Brutas!B3) -> Marissa Lima | B3: =IF(Respostas_Brutas!B3="","",IFERROR(IF(IFERROR(VALUE(TRIM(SUBSTITUTE(SUBSTITUTE(SUBSTITUTE(TRIM(Respostas_Brutas!AS3),"R$",""),".",""),",","."))),0)=0,"",(IFERROR(VALUE(TRIM(SUBSTITUTE(SUBSTITUTE(SUBSTITUTE(TRIM(Respostas_Brutas!AS3),"R$",""),".",""),",","."))),0)-IFERROR(VALUE(TRIM(SUBSTITUTE(SUBSTITUTE(SUBSTITUTE(TRIM(Respostas_Brutas!T3),"R$",""),".",""),",","."))),0))/IFERROR(VALUE(TRIM(SUBSTITUTE(SUBSTITUTE(SUBSTITUTE(TRIM(Respostas_Brutas!AS3),"R$",""),".",""),",","."))),0)),"")) | C3: =IF(Respostas_Brutas!B3="","",MIN(1,(IFERROR(VALUE(LEFT(Respostas_Brutas!I3,IFERROR(FIND(" ",Respostas_Brutas!I3)-1,LEN(Respostas_Brutas!I3)))),0)+IFERROR(VALUE(LEFT(Respostas_Brutas!O3,IFERROR(FIND(" ",Respostas_Brutas!O3)-1,LEN(Respostas_Brutas!O3)))),0))/20)) -> 0.95 | D3: =IF(Respostas_Brutas!B3="","",IF(Respostas_Brutas!D3="","",MIN(1,MAX(0,(YEAR(TODAY())-N(Respostas_Brutas!D3))/15)))) -> 0.6 | E3: =IF(Respostas_Brutas!B3="","",IF(ISNUMBER(SEARCH("Sim",Respostas_Brutas!S3)),1,0)) -> 0 | F3: =IF(Respostas_Brutas!B3="","",IFERROR(N(Respostas_Brutas!Y3)/N(Respostas_Brutas!Z3),"")) -> 0 | G3: =IF(Respostas_Brutas!B3="","",IF(Respostas_Brutas!K3<>"",1,0)) -> 1 | H3: =IF(Respostas_Brutas!B3="","",IF(ISNUMBER(SEARCH("Não",Respostas_Brutas!AH3)),1,0)) -> 0 | I3: =IF(Respostas_Brutas!B3="","",IF(ISNUMBER(SEARCH("Sim",Respostas_Brutas!AL3)),1,0)) -> 0 | J3: =IF(Respostas_Brutas!B3="","",IF(Respostas_Brutas!AN3="","",MIN(1,MAX(0,(N(Respostas_Brutas!AN3)-1)/4)))) -> 0
A4: =IF(Respostas_Brutas!B4="","",Respostas_Brutas!B4) -> Francisca ROSELI de Alcântara Madeiro | B4: =IF(Respostas_Brutas!B4="","",IFERROR(IF(IFERROR(VALUE(TRIM(SUBSTITUTE(SUBSTITUTE(SUBSTITUTE(TRIM(Respostas_Brutas!AS4),"R$",""),".",""),",","."))),0)=0,"",(IFERROR(VALUE(TRIM(SUBSTITUTE(SUBSTITUTE(SUBSTITUTE(TRIM(Respostas_Brutas!AS4),"R$",""),".",""),",","."))),0)-IFERROR(VALUE(TRIM(SUBSTITUTE(SUBSTITUTE(SUBSTITUTE(TRIM(Respostas_Brutas!T4),"R$",""),".",""),",","."))),0))/IFERROR(VALUE(TRIM(SUBSTITUTE(SUBSTITUTE(SUBSTITUTE(TRIM(Respostas_Brutas!AS4),"R$",""),".",""),",","."))),0)),"")) | C4: =IF(Respostas_Brutas!B4="","",MIN(1,(IFERROR(VALUE(LEFT(Respostas_Brutas!I4,IFERROR(FIND(" ",Respostas_Brutas!I4)-1,LEN(Respostas_Brutas!I4)))),0)+IFERROR(VALUE(LEFT(Respostas_Brutas!O4,IFERROR(FIND(" ",Respostas_Brutas!O4)-1,LEN(Respostas_Brutas!O4)))),0))/20)) -> 0 | D4: =IF(Respostas_Brutas!B4="","",IF(Respostas_Brutas!D4="","",MIN(1,MAX(0,(YEAR(TODAY())-N(Respostas_Brutas!D4))/15)))) -> 0.2 | E4: =IF(Respostas_Brutas!B4="","",IF(ISNUMBER(SEARCH("Sim",Respostas_Brutas!S4)),1,0)) -> 0 | F4: =IF(Respostas_Brutas!B4="","",IFERROR(N(Respostas_Brutas!Y4)/N(Respostas_Brutas!Z4),"")) | G4: =IF(Respostas_Brutas!B4="","",IF(Respostas_Brutas!K4<>"",1,0)) -> 1 | H4: =IF(Respostas_Brutas!B4="","",IF(ISNUMBER(SEARCH("Não",Respostas_Brutas!AH4)),1,0)) -> 0 | I4: =IF(Respostas_Brutas!B4="","",IF(ISNUMBER(SEARCH("Sim",Respostas_Brutas!AL4)),1,0)) -> 0 | J4: =IF(Respostas_Brutas!B4="","",IF(Respostas_Brutas!AN4="","",MIN(1,MAX(0,(N(Respostas_Brutas!AN4)-1)/4)))) -> 0
A5: =IF(Respostas_Brutas!B5="","",Respostas_Brutas!B5) | B5: =IF(Respostas_Brutas!B5="","",IFERROR(IF(IFERROR(VALUE(TRIM(SUBSTITUTE(SUBSTITUTE(SUBSTITUTE(TRIM(Respostas_Brutas!AS5),"R$",""),".",""),",","."))),0)=0,"",(IFERROR(VALUE(TRIM(SUBSTITUTE(SUBSTITUTE(SUBSTITUTE(TRIM(Respostas_Brutas!AS5),"R$",""),".",""),",","."))),0)-IFERROR(VALUE(TRIM(SUBSTITUTE(SUBSTITUTE(SUBSTITUTE(TRIM(Respostas_Brutas!T5),"R$",""),".",""),",","."))),0))/IFERROR(VALUE(TRIM(SUBSTITUTE(SUBSTITUTE(SUBSTITUTE(TRIM(Respostas_Brutas!AS5),"R$",""),".",""),",","."))),0)),"")) | C5: =IF(Respostas_Brutas!B5="","",MIN(1,(IFERROR(VALUE(LEFT(Respostas_Brutas!I5,IFERROR(FIND(" ",Respostas_Brutas!I5)-1,LEN(Respostas_Brutas!I5)))),0)+IFERROR(VALUE(LEFT(Respostas_Brutas!O5,IFERROR(FIND(" ",Respostas_Brutas!O5)-1,LEN(Respostas_Brutas!O5)))),0))/20)) | D5: =IF(Respostas_Brutas!B5="","",IF(Respostas_Brutas!D5="","",MIN(1,MAX(0,(YEAR(TODAY())-N(Respostas_Brutas!D5))/15)))) | E5: =IF(Respostas_Brutas!B5="","",IF(ISNUMBER(SEARCH("Sim",Respostas_Brutas!S5)),1,0)) | F5: =IF(Respostas_Brutas!B5="","",IFERROR(N(Respostas_Brutas!Y5)/N(Respostas_Brutas!Z5),"")) | G5: =IF(Respostas_Brutas!B5="","",IF(Respostas_Brutas!K5<>"",1,0)) | H5: =IF(Respostas_Brutas!B5="","",IF(ISNUMBER(SEARCH("Não",Respostas_Brutas!AH5)),1,0)) | I5: =IF(Respostas_Brutas!B5="","",IF(ISNUMBER(SEARCH("Sim",Respostas_Brutas!AL5)),1,0)) | J5: =IF(Respostas_Brutas!B5="","",IF(Respostas_Brutas!AN5="","",MIN(1,MAX(0,(N(Respostas_Brutas!AN5)-1)/4))))
A6: =IF(Respostas_Brutas!B6="","",Respostas_Brutas!B6) | B6: =IF(Respostas_Brutas!B6="","",IFERROR(IF(IFERROR(VALUE(TRIM(SUBSTITUTE(SUBSTITUTE(SUBSTITUTE(TRIM(Respostas_Brutas!AS6),"R$",""),".",""),",","."))),0)=0,"",(IFERROR(VALUE(TRIM(SUBSTITUTE(SUBSTITUTE(SUBSTITUTE(TRIM(Respostas_Brutas!AS6),"R$",""),".",""),",","."))),0)-IFERROR(VALUE(TRIM(SUBSTITUTE(SUBSTITUTE(SUBSTITUTE(TRIM(Respostas_Brutas!T6),"R$",""),".",""),",","."))),0))/IFERROR(VALUE(TRIM(SUBSTITUTE(SUBSTITUTE(SUBSTITUTE(TRIM(Respostas_Brutas!AS6),"R$",""),".",""),",","."))),0)),"")) | C6: =IF(Respostas_Brutas!B6="","",MIN(1,(IFERROR(VALUE(LEFT(Respostas_Brutas!I6,IFERROR(FIND(" ",Respostas_Brutas!I6)-1,LEN(Respostas_Brutas!I6)))),0)+IFERROR(VALUE(LEFT(Respostas_Brutas!O6,IFERROR(FIND(" ",Respostas_Brutas!O6)-1,LEN(Respostas_Brutas!O6)))),0))/20)) | D6: =IF(Respostas_Brutas!B6="","",IF(Respostas_Brutas!D6="","",MIN(1,MAX(0,(YEAR(TODAY())-N(Respostas_Brutas!D6))/15)))) | E6: =IF(Respostas_Brutas!B6="","",IF(ISNUMBER(SEARCH("Sim",Respostas_Brutas!S6)),1,0)) | F6: =IF(Respostas_Brutas!B6="","",IFERROR(N(Respostas_Brutas!Y6)/N(Respostas_Brutas!Z6),"")) | G6: =IF(Respostas_Brutas!B6="","",IF(Respostas_Brutas!K6<>"",1,0)) | H6: =IF(Respostas_Brutas!B6="","",IF(ISNUMBER(SEARCH("Não",Respostas_Brutas!AH6)),1,0)) | I6: =IF(Respostas_Brutas!B6="","",IF(ISNUMBER(SEARCH("Sim",Respostas_Brutas!AL6)),1,0)) | J6: =IF(Respostas_Brutas!B6="","",IF(Respostas_Brutas!AN6="","",MIN(1,MAX(0,(N(Respostas_Brutas!AN6)-1)/4))))
A7: =IF(Respostas_Brutas!B7="","",Respostas_Brutas!B7) | B7: =IF(Respostas_Brutas!B7="","",IFERROR(IF(IFERROR(VALUE(TRIM(SUBSTITUTE(SUBSTITUTE(SUBSTITUTE(TRIM(Respostas_Brutas!AS7),"R$",""),".",""),",","."))),0)=0,"",(IFERROR(VALUE(TRIM(SUBSTITUTE(SUBSTITUTE(SUBSTITUTE(TRIM(Respostas_Brutas!AS7),"R$",""),".",""),",","."))),0)-IFERROR(VALUE(TRIM(SUBSTITUTE(SUBSTITUTE(SUBSTITUTE(TRIM(Respostas_Brutas!T7),"R$",""),".",""),",","."))),0))/IFERROR(VALUE(TRIM(SUBSTITUTE(SUBSTITUTE(SUBSTITUTE(TRIM(Respostas_Brutas!AS7),"R$",""),".",""),",","."))),0)),"")) | C7: =IF(Respostas_Brutas!B7="","",MIN(1,(IFERROR(VALUE(LEFT(Respostas_Brutas!I7,IFERROR(FIND(" ",Respostas_Brutas!I7)-1,LEN(Respostas_Brutas!I7)))),0)+IFERROR(VALUE(LEFT(Respostas_Brutas!O7,IFERROR(FIND(" ",Respostas_Brutas!O7)-1,LEN(Respostas_Brutas!O7)))),0))/20)) | D7: =IF(Respostas_Brutas!B7="","",IF(Respostas_Brutas!D7="","",MIN(1,MAX(0,(YEAR(TODAY())-N(Respostas_Brutas!D7))/15)))) | E7: =IF(Respostas_Brutas!B7="","",IF(ISNUMBER(SEARCH("Sim",Respostas_Brutas!S7)),1,0)) | F7: =IF(Respostas_Brutas!B7="","",IFERROR(N(Respostas_Brutas!Y7)/N(Respostas_Brutas!Z7),"")) | G7: =IF(Respostas_Brutas!B7="","",IF(Respostas_Brutas!K7<>"",1,0)) | H7: =IF(Respostas_Brutas!B7="","",IF(ISNUMBER(SEARCH("Não",Respostas_Brutas!AH7)),1,0)) | I7: =IF(Respostas_Brutas!B7="","",IF(ISNUMBER(SEARCH("Sim",Respostas_Brutas!AL7)),1,0)) | J7: =IF(Respostas_Brutas!B7="","",IF(Respostas_Brutas!AN7="","",MIN(1,MAX(0,(N(Respostas_Brutas!AN7)-1)/4))))
A8: =IF(Respostas_Brutas!B8="","",Respostas_Brutas!B8) | B8: =IF(Respostas_Brutas!B8="","",IFERROR(IF(IFERROR(VALUE(TRIM(SUBSTITUTE(SUBSTITUTE(SUBSTITUTE(TRIM(Respostas_Brutas!AS8),"R$",""),".",""),",","."))),0)=0,"",(IFERROR(VALUE(TRIM(SUBSTITUTE(SUBSTITUTE(SUBSTITUTE(TRIM(Respostas_Brutas!AS8),"R$",""),".",""),",","."))),0)-IFERROR(VALUE(TRIM(SUBSTITUTE(SUBSTITUTE(SUBSTITUTE(TRIM(Respostas_Brutas!T8),"R$",""),".",""),",","."))),0))/IFERROR(VALUE(TRIM(SUBSTITUTE(SUBSTITUTE(SUBSTITUTE(TRIM(Respostas_Brutas!AS8),"R$",""),".",""),",","."))),0)),"")) | C8: =IF(Respostas_Brutas!B8="","",MIN(1,(IFERROR(VALUE(LEFT(Respostas_Brutas!I8,IFERROR(FIND(" ",Respostas_Brutas!I8)-1,LEN(Respostas_Brutas!I8)))),0)+IFERROR(VALUE(LEFT(Respostas_Brutas!O8,IFERROR(FIND(" ",Respostas_Brutas!O8)-1,LEN(Respostas_Brutas!O8)))),0))/20)) | D8: =IF(Respostas_Brutas!B8="","",IF(Respostas_Brutas!D8="","",MIN(1,MAX(0,(YEAR(TODAY())-N(Respostas_Brutas!D8))/15)))) | E8: =IF(Respostas_Brutas!B8="","",IF(ISNUMBER(SEARCH("Sim",Respostas_Brutas!S8)),1,0)) | F8: =IF(Respostas_Brutas!B8="","",IFERROR(N(Respostas_Brutas!Y8)/N(Respostas_Brutas!Z8),"")) | G8: =IF(Respostas_Brutas!B8="","",IF(Respostas_Brutas!K8<>"",1,0)) | H8: =IF(Respostas_Brutas!B8="","",IF(ISNUMBER(SEARCH("Não",Respostas_Brutas!AH8)),1,0)) | I8: =IF(Respostas_Brutas!B8="","",IF(ISNUMBER(SEARCH("Sim",Respostas_Brutas!AL8)),1,0)) | J8: =IF(Respostas_Brutas!B8="","",IF(Respostas_Brutas!AN8="","",MIN(1,MAX(0,(N(Respostas_Brutas!AN8)-1)/4))))
A9: =IF(Respostas_Brutas!B9="","",Respostas_Brutas!B9) | B9: =IF(Respostas_Brutas!B9="","",IFERROR(IF(IFERROR(VALUE(TRIM(SUBSTITUTE(SUBSTITUTE(SUBSTITUTE(TRIM(Respostas_Brutas!AS9),"R$",""),".",""),",","."))),0)=0,"",(IFERROR(VALUE(TRIM(SUBSTITUTE(SUBSTITUTE(SUBSTITUTE(TRIM(Respostas_Brutas!AS9),"R$",""),".",""),",","."))),0)-IFERROR(VALUE(TRIM(SUBSTITUTE(SUBSTITUTE(SUBSTITUTE(TRIM(Respostas_Brutas!T9),"R$",""),".",""),",","."))),0))/IFERROR(VALUE(TRIM(SUBSTITUTE(SUBSTITUTE(SUBSTITUTE(TRIM(Respostas_Brutas!AS9),"R$",""),".",""),",","."))),0)),"")) | C9: =IF(Respostas_Brutas!B9="","",MIN(1,(IFERROR(VALUE(LEFT(Respostas_Brutas!I9,IFERROR(FIND(" ",Respostas_Brutas!I9)-1,LEN(Respostas_Brutas!I9)))),0)+IFERROR(VALUE(LEFT(Respostas_Brutas!O9,IFERROR(FIND(" ",Respostas_Brutas!O9)-1,LEN(Respostas_Brutas!O9)))),0))/20)) | D9: =IF(Respostas_Brutas!B9="","",IF(Respostas_Brutas!D9="","",MIN(1,MAX(0,(YEAR(TODAY())-N(Respostas_Brutas!D9))/15)))) | E9: =IF(Respostas_Brutas!B9="","",IF(ISNUMBER(SEARCH("Sim",Respostas_Brutas!S9)),1,0)) | F9: =IF(Respostas_Brutas!B9="","",IFERROR(N(Respostas_Brutas!Y9)/N(Respostas_Brutas!Z9),"")) | G9: =IF(Respostas_Brutas!B9="","",IF(Respostas_Brutas!K9<>"",1,0)) | H9: =IF(Respostas_Brutas!B9="","",IF(ISNUMBER(SEARCH("Não",Respostas_Brutas!AH9)),1,0)) | I9: =IF(Respostas_Brutas!B9="","",IF(ISNUMBER(SEARCH("Sim",Respostas_Brutas!AL9)),1,0)) | J9: =IF(Respostas_Brutas!B9="","",IF(Respostas_Brutas!AN9="","",MIN(1,MAX(0,(N(Respostas_Brutas!AN9)-1)/4))))
A10: =IF(Respostas_Brutas!B10="","",Respostas_Brutas!B10) | B10: =IF(Respostas_Brutas!B10="","",IFERROR(IF(IFERROR(VALUE(TRIM(SUBSTITUTE(SUBSTITUTE(SUBSTITUTE(TRIM(Respostas_Brutas!AS10),"R$",""),".",""),",","."))),0)=0,"",(IFERROR(VALUE(TRIM(SUBSTITUTE(SUBSTITUTE(SUBSTITUTE(TRIM(Respostas_Brutas!AS10),"R$",""),".",""),",","."))),0)-IFERROR(VALUE(TRIM(SUBSTITUTE(SUBSTITUTE(SUBSTITUTE(TRIM(Respostas_Brutas!T10),"R$",""),".",""),",","."))),0))/IFERROR(VALUE(TRIM(SUBSTITUTE(SUBSTITUTE(SUBSTITUTE(TRIM(Respostas_Brutas!AS10),"R$",""),".",""),",","."))),0)),"")) | C10: =IF(Respostas_Brutas!B10="","",MIN(1,(IFERROR(VALUE(LEFT(Respostas_Brutas!I10,IFERROR(FIND(" ",Respostas_Brutas!I10)-1,LEN(Respostas_Brutas!I10)))),0)+IFERROR(VALUE(LEFT(Respostas_Brutas!O10,IFERROR(FIND(" ",Respostas_Brutas!O10)-1,LEN(Respostas_Brutas!O10)))),0))/20)) | D10: =IF(Respostas_Brutas!B10="","",IF(Respostas_Brutas!D10="","",MIN(1,MAX(0,(YEAR(TODAY())-N(Respostas_Brutas!D10))/15)))) | E10: =IF(Respostas_Brutas!B10="","",IF(ISNUMBER(SEARCH("Sim",Respostas_Brutas!S10)),1,0)) | F10: =IF(Respostas_Brutas!B10="","",IFERROR(N(Respostas_Brutas!Y10)/N(Respostas_Brutas!Z10),"")) | G10: =IF(Respostas_Brutas!B10="","",IF(Respostas_Brutas!K10<>"",1,0)) | H10: =IF(Respostas_Brutas!B10="","",IF(ISNUMBER(SEARCH("Não",Respostas_Brutas!AH10)),1,0)) | I10: =IF(Respostas_Brutas!B10="","",IF(ISNUMBER(SEARCH("Sim",Respostas_Brutas!AL10)),1,0)) | J10: =IF(Respostas_Brutas!B10="","",IF(Respostas_Brutas!AN10="","",MIN(1,MAX(0,(N(Respostas_Brutas!AN10)-1)/4))))
A11: =IF(Respostas_Brutas!B11="","",Respostas_Brutas!B11) | B11: =IF(Respostas_Brutas!B11="","",IFERROR(IF(IFERROR(VALUE(TRIM(SUBSTITUTE(SUBSTITUTE(SUBSTITUTE(TRIM(Respostas_Brutas!AS11),"R$",""),".",""),",","."))),0)=0,"",(IFERROR(VALUE(TRIM(SUBSTITUTE(SUBSTITUTE(SUBSTITUTE(TRIM(Respostas_Brutas!AS11),"R$",""),".",""),",","."))),0)-IFERROR(VALUE(TRIM(SUBSTITUTE(SUBSTITUTE(SUBSTITUTE(TRIM(Respostas_Brutas!T11),"R$",""),".",""),",","."))),0))/IFERROR(VALUE(TRIM(SUBSTITUTE(SUBSTITUTE(SUBSTITUTE(TRIM(Respostas_Brutas!AS11),"R$",""),".",""),",","."))),0)),"")) | C11: =IF(Respostas_Brutas!B11="","",MIN(1,(IFERROR(VALUE(LEFT(Respostas_Brutas!I11,IFERROR(FIND(" ",Respostas_Brutas!I11)-1,LEN(Respostas_Brutas!I11)))),0)+IFERROR(VALUE(LEFT(Respostas_Brutas!O11,IFERROR(FIND(" ",Respostas_Brutas!O11)-1,LEN(Respostas_Brutas!O11)))),0))/20)) | D11: =IF(Respostas_Brutas!B11="","",IF(Respostas_Brutas!D11="","",MIN(1,MAX(0,(YEAR(TODAY())-N(Respostas_Brutas!D11))/15)))) | E11: =IF(Respostas_Brutas!B11="","",IF(ISNUMBER(SEARCH("Sim",Respostas_Brutas!S11)),1,0)) | F11: =IF(Respostas_Brutas!B11="","",IFERROR(N(Respostas_Brutas!Y11)/N(Respostas_Brutas!Z11),"")) | G11: =IF(Respostas_Brutas!B11="","",IF(Respostas_Brutas!K11<>"",1,0)) | H11: =IF(Respostas_Brutas!B11="","",IF(ISNUMBER(SEARCH("Não",Respostas_Brutas!AH11)),1,0)) | I11: =IF(Respostas_Brutas!B11="","",IF(ISNUMBER(SEARCH("Sim",Respostas_Brutas!AL11)),1,0)) | J11: =IF(Respostas_Brutas!B11="","",IF(Respostas_Brutas!AN11="","",MIN(1,MAX(0,(N(Respostas_Brutas!AN11)-1)/4))))
A12: =IF(Respostas_Brutas!B12="","",Respostas_Brutas!B12) | B12: =IF(Respostas_Brutas!B12="","",IFERROR(IF(IFERROR(VALUE(TRIM(SUBSTITUTE(SUBSTITUTE(SUBSTITUTE(TRIM(Respostas_Brutas!AS12),"R$",""),".",""),",","."))),0)=0,"",(IFERROR(VALUE(TRIM(SUBSTITUTE(SUBSTITUTE(SUBSTITUTE(TRIM(Respostas_Brutas!AS12),"R$",""),".",""),",","."))),0)-IFERROR(VALUE(TRIM(SUBSTITUTE(SUBSTITUTE(SUBSTITUTE(TRIM(Respostas_Brutas!T12),"R$",""),".",""),",","."))),0))/IFERROR(VALUE(TRIM(SUBSTITUTE(SUBSTITUTE(SUBSTITUTE(TRIM(Respostas_Brutas!AS12),"R$",""),".",""),",","."))),0)),"")) | C12: =IF(Respostas_Brutas!B12="","",MIN(1,(IFERROR(VALUE(LEFT(Respostas_Brutas!I12,IFERROR(FIND(" ",Respostas_Brutas!I12)-1,LEN(Respostas_Brutas!I12)))),0)+IFERROR(VALUE(LEFT(Respostas_Brutas!O12,IFERROR(FIND(" ",Respostas_Brutas!O12)-1,LEN(Respostas_Brutas!O12)))),0))/20)) | D12: =IF(Respostas_Brutas!B12="","",IF(Respostas_Brutas!D12="","",MIN(1,MAX(0,(YEAR(TODAY())-N(Respostas_Brutas!D12))/15)))) | E12: =IF(Respostas_Brutas!B12="","",IF(ISNUMBER(SEARCH("Sim",Respostas_Brutas!S12)),1,0)) | F12: =IF(Respostas_Brutas!B12="","",IFERROR(N(Respostas_Brutas!Y12)/N(Respostas_Brutas!Z12),"")) | G12: =IF(Respostas_Brutas!B12="","",IF(Respostas_Brutas!K12<>"",1,0)) | H12: =IF(Respostas_Brutas!B12="","",IF(ISNUMBER(SEARCH("Não",Respostas_Brutas!AH12)),1,0)) | I12: =IF(Respostas_Brutas!B12="","",IF(ISNUMBER(SEARCH("Sim",Respostas_Brutas!AL12)),1,0)) | J12: =IF(Respostas_Brutas!B12="","",IF(Respostas_Brutas!AN12="","",MIN(1,MAX(0,(N(Respostas_Brutas!AN12)-1)/4))))
A13: =IF(Respostas_Brutas!B13="","",Respostas_Brutas!B13) | B13: =IF(Respostas_Brutas!B13="","",IFERROR(IF(IFERROR(VALUE(TRIM(SUBSTITUTE(SUBSTITUTE(SUBSTITUTE(TRIM(Respostas_Brutas!AS13),"R$",""),".",""),",","."))),0)=0,"",(IFERROR(VALUE(TRIM(SUBSTITUTE(SUBSTITUTE(SUBSTITUTE(TRIM(Respostas_Brutas!AS13),"R$",""),".",""),",","."))),0)-IFERROR(VALUE(TRIM(SUBSTITUTE(SUBSTITUTE(SUBSTITUTE(TRIM(Respostas_Brutas!T13),"R$",""),".",""),",","."))),0))/IFERROR(VALUE(TRIM(SUBSTITUTE(SUBSTITUTE(SUBSTITUTE(TRIM(Respostas_Brutas!AS13),"R$",""),".",""),",","."))),0)),"")) | C13: =IF(Respostas_Brutas!B13="","",MIN(1,(IFERROR(VALUE(LEFT(Respostas_Brutas!I13,IFERROR(FIND(" ",Respostas_Brutas!I13)-1,LEN(Respostas_Brutas!I13)))),0)+IFERROR(VALUE(LEFT(Respostas_Brutas!O13,IFERROR(FIND(" ",Respostas_Brutas!O13)-1,LEN(Respostas_Brutas!O13)))),0))/20)) | D13: =IF(Respostas_Brutas!B13="","",IF(Respostas_Brutas!D13="","",MIN(1,MAX(0,(YEAR(TODAY())-N(Respostas_Brutas!D13))/15)))) | E13: =IF(Respostas_Brutas!B13="","",IF(ISNUMBER(SEARCH("Sim",Respostas_Brutas!S13)),1,0)) | F13: =IF(Respostas_Brutas!B13="","",IFERROR(N(Respostas_Brutas!Y13)/N(Respostas_Brutas!Z13),"")) | G13: =IF(Respostas_Brutas!B13="","",IF(Respostas_Brutas!K13<>"",1,0)) | H13: =IF(Respostas_Brutas!B13="","",IF(ISNUMBER(SEARCH("Não",Respostas_Brutas!AH13)),1,0)) | I13: =IF(Respostas_Brutas!B13="","",IF(ISNUMBER(SEARCH("Sim",Respostas_Brutas!AL13)),1,0)) | J13: =IF(Respostas_Brutas!B13="","",IF(Respostas_Brutas!AN13="","",MIN(1,MAX(0,(N(Respostas_Brutas!AN13)-1)/4))))
... A501: =IF(Respostas_Brutas!B501="","",Respostas_Brutas!B501) | B501: =IF(Respostas_Brutas!B501="","",IFERROR(IF(IFERROR(VALUE(TRIM(SUBSTITUTE(SUBSTITUTE(SUBSTITUTE(TRIM(Respostas_Brutas!AS501),"R$",""),".",""),",","."))),0)=0,"",(IFERROR(VALUE(TRIM(SUBSTITUTE(SUBSTITUTE(SUBSTITUTE(TRIM(Respostas_Brutas!AS501),"R$",""),".",""),",","."))),0)-IFERROR(VALUE(TRIM(SUBSTITUTE(SUBSTITUTE(SUBSTITUTE(TRIM(Respostas_Brutas!T501),"R$",""),".",""),",","."))),0))/IFERROR(VALUE(TRIM(SUBSTITUTE(SUBSTITUTE(SUBSTITUTE(TRIM(Respostas_Brutas!AS501),"R$",""),".",""),",","."))),0)),"")) | C501: =IF(Respostas_Brutas!B501="","",MIN(1,(IFERROR(VALUE(LEFT(Respostas_Brutas!I501,IFERROR(FIND(" ",Respostas_Brutas!I501)-1,LEN(Respostas_Brutas!I501)))),0)+IFERROR(VALUE(LEFT(Respostas_Brutas!O501,IFERROR(FIND(" ",Respostas_Brutas!O501)-1,LEN(Respostas_Brutas!O501)))),0))/20)) | D501: =IF(Respostas_Brutas!B501="","",IF(Respostas_Brutas!D501="","",MIN(1,MAX(0,(YEAR(TODAY())-N(Respostas_Brutas!D501))/15)))) | E501: =IF(Respostas_Brutas!B501="","",IF(ISNUMBER(SEARCH("Sim",Respostas_Brutas!S501)),1,0)) | F501: =IF(Respostas_Brutas!B501="","",IFERROR(N(Respostas_Brutas!Y501)/N(Respostas_Brutas!Z501),"")) | G501: =IF(Respostas_Brutas!B501="","",IF(Respostas_Brutas!K501<>"",1,0)) | H501: =IF(Respostas_Brutas!B501="","",IF(ISNUMBER(SEARCH("Não",Respostas_Brutas!AH501)),1,0)) | I501: =IF(Respostas_Brutas!B501="","",IF(ISNUMBER(SEARCH("Sim",Respostas_Brutas!AL501)),1,0)) | J501: =IF(Respostas_Brutas!B501="","",IF(Respostas_Brutas!AN501="","",MIN(1,MAX(0,(N(Respostas_Brutas!AN501)-1)/4))))
A502: Fórmulas só na linha 2 — espalham sozinhas no Google Sheets. Não copiar para outras linhas.
A503: V9 assume resposta numérica (1-5) para 'autoridade digital'. Se for texto no seu Forms, esta fórmula precisa mudar.

Sheet Pesos_Decisao
A1: Decisão | B1: V1_GapReceita (0-1) | C1: V2_ClientesAtuais | D1: V3_TempoAtuacao_anos | E1: V4_DependeUmServico (0/1) | F1: V5_TaxaOcupacao (0-1) | G1: V6_TemMaisDeUmServico (0/1) | H1: V7_SemRegraReajuste (0/1) | I1: V8_IdentificouDiferencial (0/1) | J1: V9_AutoridadeDigital (1-5)
A2: Captar | B2: 3 | C2: -2 | D2: -1 | E2: 1 | F2: 1 | G2: -1 | H2: 0 | I2: 0 | J2: 1
A3: Precificar | B3: 1 | C3: 0 | D3: 0 | E3: 0 | F3: -1 | G3: 0 | H3: 3 | I3: 1 | J3: 1
A4: Posicionar | B4: 0 | C4: 0 | D4: 1 | E4: 3 | F4: 1 | G4: 0 | H4: 0 | I4: 2 | J4: 0
A5: Produto-Vitrine | B5: 1 | C5: 0 | D5: 0 | E5: 1 | F5: 0 | G5: 2 | H5: 0 | I5: 1 | J5: 0
A6: Mix | B6: 1 | C6: -1 | D6: 0 | E6: 1 | F6: 0 | G6: 2 | H6: 0 | I6: 1 | J6: 0
A7: Esteira | B7: 0 | C7: 1 | D7: 1 | E7: 0 | F7: -1 | G7: 2 | H7: 0 | I7: 1 | J7: 1
A8: Escalar | B8: 0 | C8: 2 | D8: 2 | E8: 0 | F8: -2 | G8: 0 | H8: -1 | I8: 2 | J8: 2
A11: Pesos de exemplo, heurísticos. Ajuste com base na sua experiência — esta aba nunca é automática.

Sheet Pontuacao
A1: Cliente | B1: Captar | C1: Precificar | D1: Posicionar | E1: Produto-Vitrine | F1: Mix | G1: Esteira | H1: Escalar
A2: =IF(Variaveis!A2="","",Variaveis!A2) -> Sannara Freitas | B2: =IF(Variaveis!A2="","",SUMPRODUCT(N(Variaveis!B2:J2),Pesos_Decisao!$B$2:$J$2)) -> 0.85 | C2: =IF(Variaveis!A2="","",SUMPRODUCT(N(Variaveis!B2:J2),Pesos_Decisao!$B$3:$J$3)) -> -0.25 | D2: =IF(Variaveis!A2="","",SUMPRODUCT(N(Variaveis!B2:J2),Pesos_Decisao!$B$4:$J$4)) -> 3.25 | E2: =IF(Variaveis!A2="","",SUMPRODUCT(N(Variaveis!B2:J2),Pesos_Decisao!$B$5:$J$5)) -> 1 | F2: =IF(Variaveis!A2="","",SUMPRODUCT(N(Variaveis!B2:J2),Pesos_Decisao!$B$6:$J$6)) -> 0.8 | G2: =IF(Variaveis!A2="","",SUMPRODUCT(N(Variaveis!B2:J2),Pesos_Decisao!$B$7:$J$7)) -> -0.05 | H2: =IF(Variaveis!A2="","",SUMPRODUCT(N(Variaveis!B2:J2),Pesos_Decisao!$B$8:$J$8)) -> -0.1
A3: =IF(Variaveis!A3="","",Variaveis!A3) -> Marissa Lima | B3: =IF(Variaveis!A3="","",SUMPRODUCT(N(Variaveis!B3:J3),Pesos_Decisao!$B$2:$J$2)) -> -3.5 | C3: =IF(Variaveis!A3="","",SUMPRODUCT(N(Variaveis!B3:J3),Pesos_Decisao!$B$3:$J$3)) -> 0 | D3: =IF(Variaveis!A3="","",SUMPRODUCT(N(Variaveis!B3:J3),Pesos_Decisao!$B$4:$J$4)) -> 0.6 | E3: =IF(Variaveis!A3="","",SUMPRODUCT(N(Variaveis!B3:J3),Pesos_Decisao!$B$5:$J$5)) -> 2 | F3: =IF(Variaveis!A3="","",SUMPRODUCT(N(Variaveis!B3:J3),Pesos_Decisao!$B$6:$J$6)) -> 1.05 | G3: =IF(Variaveis!A3="","",SUMPRODUCT(N(Variaveis!B3:J3),Pesos_Decisao!$B$7:$J$7)) -> 3.55 | H3: =IF(Variaveis!A3="","",SUMPRODUCT(N(Variaveis!B3:J3),Pesos_Decisao!$B$8:$J$8)) -> 3.1
A4: =IF(Variaveis!A4="","",Variaveis!A4) -> Francisca ROSELI de Alcântara Madeiro | B4: =IF(Variaveis!A4="","",SUMPRODUCT(N(Variaveis!B4:J4),Pesos_Decisao!$B$2:$J$2)) -> -1.2 | C4: =IF(Variaveis!A4="","",SUMPRODUCT(N(Variaveis!B4:J4),Pesos_Decisao!$B$3:$J$3)) -> 0 | D4: =IF(Variaveis!A4="","",SUMPRODUCT(N(Variaveis!B4:J4),Pesos_Decisao!$B$4:$J$4)) -> 0.2 | E4: =IF(Variaveis!A4="","",SUMPRODUCT(N(Variaveis!B4:J4),Pesos_Decisao!$B$5:$J$5)) -> 2 | F4: =IF(Variaveis!A4="","",SUMPRODUCT(N(Variaveis!B4:J4),Pesos_Decisao!$B$6:$J$6)) -> 2 | G4: =IF(Variaveis!A4="","",SUMPRODUCT(N(Variaveis!B4:J4),Pesos_Decisao!$B$7:$J$7)) -> 2.2 | H4: =IF(Variaveis!A4="","",SUMPRODUCT(N(Variaveis!B4:J4),Pesos_Decisao!$B$8:$J$8)) -> 0.4
A5: =IF(Variaveis!A5="","",Variaveis!A5) | B5: =IF(Variaveis!A5="","",SUMPRODUCT(N(Variaveis!B5:J5),Pesos_Decisao!$B$2:$J$2)) | C5: =IF(Variaveis!A5="","",SUMPRODUCT(N(Variaveis!B5:J5),Pesos_Decisao!$B$3:$J$3)) | D5: =IF(Variaveis!A5="","",SUMPRODUCT(N(Variaveis!B5:J5),Pesos_Decisao!$B$4:$J$4)) | E5: =IF(Variaveis!A5="","",SUMPRODUCT(N(Variaveis!B5:J5),Pesos_Decisao!$B$5:$J$5)) | F5: =IF(Variaveis!A5="","",SUMPRODUCT(N(Variaveis!B5:J5),Pesos_Decisao!$B$6:$J$6)) | G5: =IF(Variaveis!A5="","",SUMPRODUCT(N(Variaveis!B5:J5),Pesos_Decisao!$B$7:$J$7)) | H5: =IF(Variaveis!A5="","",SUMPRODUCT(N(Variaveis!B5:J5),Pesos_Decisao!$B$8:$J$8))
A6: =IF(Variaveis!A6="","",Variaveis!A6) | B6: =IF(Variaveis!A6="","",SUMPRODUCT(N(Variaveis!B6:J6),Pesos_Decisao!$B$2:$J$2)) | C6: =IF(Variaveis!A6="","",SUMPRODUCT(N(Variaveis!B6:J6),Pesos_Decisao!$B$3:$J$3)) | D6: =IF(Variaveis!A6="","",SUMPRODUCT(N(Variaveis!B6:J6),Pesos_Decisao!$B$4:$J$4)) | E6: =IF(Variaveis!A6="","",SUMPRODUCT(N(Variaveis!B6:J6),Pesos_Decisao!$B$5:$J$5)) | F6: =IF(Variaveis!A6="","",SUMPRODUCT(N(Variaveis!B6:J6),Pesos_Decisao!$B$6:$J$6)) | G6: =IF(Variaveis!A6="","",SUMPRODUCT(N(Variaveis!B6:J6),Pesos_Decisao!$B$7:$J$7)) | H6: =IF(Variaveis!A6="","",SUMPRODUCT(N(Variaveis!B6:J6),Pesos_Decisao!$B$8:$J$8))
A7: =IF(Variaveis!A7="","",Variaveis!A7) | B7: =IF(Variaveis!A7="","",SUMPRODUCT(N(Variaveis!B7:J7),Pesos_Decisao!$B$2:$J$2)) | C7: =IF(Variaveis!A7="","",SUMPRODUCT(N(Variaveis!B7:J7),Pesos_Decisao!$B$3:$J$3)) | D7: =IF(Variaveis!A7="","",SUMPRODUCT(N(Variaveis!B7:J7),Pesos_Decisao!$B$4:$J$4)) | E7: =IF(Variaveis!A7="","",SUMPRODUCT(N(Variaveis!B7:J7),Pesos_Decisao!$B$5:$J$5)) | F7: =IF(Variaveis!A7="","",SUMPRODUCT(N(Variaveis!B7:J7),Pesos_Decisao!$B$6:$J$6)) | G7: =IF(Variaveis!A7="","",SUMPRODUCT(N(Variaveis!B7:J7),Pesos_Decisao!$B$7:$J$7)) | H7: =IF(Variaveis!A7="","",SUMPRODUCT(N(Variaveis!B7:J7),Pesos_Decisao!$B$8:$J$8))
A8: =IF(Variaveis!A8="","",Variaveis!A8) | B8: =IF(Variaveis!A8="","",SUMPRODUCT(N(Variaveis!B8:J8),Pesos_Decisao!$B$2:$J$2)) | C8: =IF(Variaveis!A8="","",SUMPRODUCT(N(Variaveis!B8:J8),Pesos_Decisao!$B$3:$J$3)) | D8: =IF(Variaveis!A8="","",SUMPRODUCT(N(Variaveis!B8:J8),Pesos_Decisao!$B$4:$J$4)) | E8: =IF(Variaveis!A8="","",SUMPRODUCT(N(Variaveis!B8:J8),Pesos_Decisao!$B$5:$J$5)) | F8: =IF(Variaveis!A8="","",SUMPRODUCT(N(Variaveis!B8:J8),Pesos_Decisao!$B$6:$J$6)) | G8: =IF(Variaveis!A8="","",SUMPRODUCT(N(Variaveis!B8:J8),Pesos_Decisao!$B$7:$J$7)) | H8: =IF(Variaveis!A8="","",SUMPRODUCT(N(Variaveis!B8:J8),Pesos_Decisao!$B$8:$J$8))
A9: =IF(Variaveis!A9="","",Variaveis!A9) | B9: =IF(Variaveis!A9="","",SUMPRODUCT(N(Variaveis!B9:J9),Pesos_Decisao!$B$2:$J$2)) | C9: =IF(Variaveis!A9="","",SUMPRODUCT(N(Variaveis!B9:J9),Pesos_Decisao!$B$3:$J$3)) | D9: =IF(Variaveis!A9="","",SUMPRODUCT(N(Variaveis!B9:J9),Pesos_Decisao!$B$4:$J$4)) | E9: =IF(Variaveis!A9="","",SUMPRODUCT(N(Variaveis!B9:J9),Pesos_Decisao!$B$5:$J$5)) | F9: =IF(Variaveis!A9="","",SUMPRODUCT(N(Variaveis!B9:J9),Pesos_Decisao!$B$6:$J$6)) | G9: =IF(Variaveis!A9="","",SUMPRODUCT(N(Variaveis!B9:J9),Pesos_Decisao!$B$7:$J$7)) | H9: =IF(Variaveis!A9="","",SUMPRODUCT(N(Variaveis!B9:J9),Pesos_Decisao!$B$8:$J$8))
A10: =IF(Variaveis!A10="","",Variaveis!A10) | B10: =IF(Variaveis!A10="","",SUMPRODUCT(N(Variaveis!B10:J10),Pesos_Decisao!$B$2:$J$2)) | C10: =IF(Variaveis!A10="","",SUMPRODUCT(N(Variaveis!B10:J10),Pesos_Decisao!$B$3:$J$3)) | D10: =IF(Variaveis!A10="","",SUMPRODUCT(N(Variaveis!B10:J10),Pesos_Decisao!$B$4:$J$4)) | E10: =IF(Variaveis!A10="","",SUMPRODUCT(N(Variaveis!B10:J10),Pesos_Decisao!$B$5:$J$5)) | F10: =IF(Variaveis!A10="","",SUMPRODUCT(N(Variaveis!B10:J10),Pesos_Decisao!$B$6:$J$6)) | G10: =IF(Variaveis!A10="","",SUMPRODUCT(N(Variaveis!B10:J10),Pesos_Decisao!$B$7:$J$7)) | H10: =IF(Variaveis!A10="","",SUMPRODUCT(N(Variaveis!B10:J10),Pesos_Decisao!$B$8:$J$8))
A11: =IF(Variaveis!A11="","",Variaveis!A11) | B11: =IF(Variaveis!A11="","",SUMPRODUCT(N(Variaveis!B11:J11),Pesos_Decisao!$B$2:$J$2)) | C11: =IF(Variaveis!A11="","",SUMPRODUCT(N(Variaveis!B11:J11),Pesos_Decisao!$B$3:$J$3)) | D11: =IF(Variaveis!A11="","",SUMPRODUCT(N(Variaveis!B11:J11),Pesos_Decisao!$B$4:$J$4)) | E11: =IF(Variaveis!A11="","",SUMPRODUCT(N(Variaveis!B11:J11),Pesos_Decisao!$B$5:$J$5)) | F11: =IF(Variaveis!A11="","",SUMPRODUCT(N(Variaveis!B11:J11),Pesos_Decisao!$B$6:$J$6)) | G11: =IF(Variaveis!A11="","",SUMPRODUCT(N(Variaveis!B11:J11),Pesos_Decisao!$B$7:$J$7)) | H11: =IF(Variaveis!A11="","",SUMPRODUCT(N(Variaveis!B11:J11),Pesos_Decisao!$B$8:$J$8))
A12: =IF(Variaveis!A12="","",Variaveis!A12) | B12: =IF(Variaveis!A12="","",SUMPRODUCT(N(Variaveis!B12:J12),Pesos_Decisao!$B$2:$J$2)) | C12: =IF(Variaveis!A12="","",SUMPRODUCT(N(Variaveis!B12:J12),Pesos_Decisao!$B$3:$J$3)) | D12: =IF(Variaveis!A12="","",SUMPRODUCT(N(Variaveis!B12:J12),Pesos_Decisao!$B$4:$J$4)) | E12: =IF(Variaveis!A12="","",SUMPRODUCT(N(Variaveis!B12:J12),Pesos_Decisao!$B$5:$J$5)) | F12: =IF(Variaveis!A12="","",SUMPRODUCT(N(Variaveis!B12:J12),Pesos_Decisao!$B$6:$J$6)) | G12: =IF(Variaveis!A12="","",SUMPRODUCT(N(Variaveis!B12:J12),Pesos_Decisao!$B$7:$J$7)) | H12: =IF(Variaveis!A12="","",SUMPRODUCT(N(Variaveis!B12:J12),Pesos_Decisao!$B$8:$J$8))
A13: =IF(Variaveis!A13="","",Variaveis!A13) | B13: =IF(Variaveis!A13="","",SUMPRODUCT(N(Variaveis!B13:J13),Pesos_Decisao!$B$2:$J$2)) | C13: =IF(Variaveis!A13="","",SUMPRODUCT(N(Variaveis!B13:J13),Pesos_Decisao!$B$3:$J$3)) | D13: =IF(Variaveis!A13="","",SUMPRODUCT(N(Variaveis!B13:J13),Pesos_Decisao!$B$4:$J$4)) | E13: =IF(Variaveis!A13="","",SUMPRODUCT(N(Variaveis!B13:J13),Pesos_Decisao!$B$5:$J$5)) | F13: =IF(Variaveis!A13="","",SUMPRODUCT(N(Variaveis!B13:J13),Pesos_Decisao!$B$6:$J$6)) | G13: =IF(Variaveis!A13="","",SUMPRODUCT(N(Variaveis!B13:J13),Pesos_Decisao!$B$7:$J$7)) | H13: =IF(Variaveis!A13="","",SUMPRODUCT(N(Variaveis!B13:J13),Pesos_Decisao!$B$8:$J$8))
... A501: =IF(Variaveis!A501="","",Variaveis!A501) | B501: =IF(Variaveis!A501="","",SUMPRODUCT(N(Variaveis!B501:J501),Pesos_Decisao!$B$2:$J$2)) | C501: =IF(Variaveis!A501="","",SUMPRODUCT(N(Variaveis!B501:J501),Pesos_Decisao!$B$3:$J$3)) | D501: =IF(Variaveis!A501="","",SUMPRODUCT(N(Variaveis!B501:J501),Pesos_Decisao!$B$4:$J$4)) | E501: =IF(Variaveis!A501="","",SUMPRODUCT(N(Variaveis!B501:J501),Pesos_Decisao!$B$5:$J$5)) | F501: =IF(Variaveis!A501="","",SUMPRODUCT(N(Variaveis!B501:J501),Pesos_Decisao!$B$6:$J$6)) | G501: =IF(Variaveis!A501="","",SUMPRODUCT(N(Variaveis!B501:J501),Pesos_Decisao!$B$7:$J$7)) | H501: =IF(Variaveis!A501="","",SUMPRODUCT(N(Variaveis!B501:J501),Pesos_Decisao!$B$8:$J$8))
A502: Fórmulas só na linha 2 — espalham sozinhas.

Sheet Historico
A1: Cliente | B1: Checkpoint | C1: Decisão priorizada | D1: Score na decisão | E1: Resultado (Sucesso/Falhou/Em curso) | F1: Observação
A14: Preencha uma linha por checkpoint concluído (copie a decisão/score de Diagnostico).

Sheet Diagnostico
A1: Cliente | B1: Decisão prioritária | C1: Score | D1: Probabilidade de sucesso | E1: Diagnóstico (texto)
A2: =IF(Pontuacao!A2="","",Pontuacao!A2) -> Sannara Freitas | B2: {=IFERROR(IF(A2="","",INDEX(Pontuacao!$B$1:$H$1,MATCH(MAX(Pontuacao!B2:H2),Pontuacao!B2:H2,0))),"")} -> Posicionar | C2: =IF(A2="","",MAX(Pontuacao!B2:H2)) -> 3.25 | D2: =IF(A2="","","Aguardando histórico (mín. ~50-100 casos)") -> Aguardando histórico (mín. ~50-100 casos) | E2: =IF(A2="","",CONCATENATE("Prioridade: ",B2," (score ",TEXT(C2,"0.0"),"). Maior aderência com o perfil atual dessa cliente.")) -> Prioridade: Posicionar (score 3,3). Maior aderência com o perfil atual dessa cliente.
A3: =IF(Pontuacao!A3="","",Pontuacao!A3) -> Marissa Lima | B3: {=IFERROR(IF(A3="","",INDEX(Pontuacao!$B$1:$H$1,MATCH(MAX(Pontuacao!B3:H3),Pontuacao!B3:H3,0))),"")} -> Esteira | C3: =IF(A3="","",MAX(Pontuacao!B3:H3)) -> 3.55 | D3: =IF(A3="","","Aguardando histórico (mín. ~50-100 casos)") -> Aguardando histórico (mín. ~50-100 casos) | E3: =IF(A3="","",CONCATENATE("Prioridade: ",B3," (score ",TEXT(C3,"0.0"),"). Maior aderência com o perfil atual dessa cliente.")) -> Prioridade: Esteira (score 3,6). Maior aderência com o perfil atual dessa cliente.
A4: =IF(Pontuacao!A4="","",Pontuacao!A4) -> Francisca ROSELI de Alcântara Madeiro | B4: {=IFERROR(IF(A4="","",INDEX(Pontuacao!$B$1:$H$1,MATCH(MAX(Pontuacao!B4:H4),Pontuacao!B4:H4,0))),"")} -> Esteira | C4: =IF(A4="","",MAX(Pontuacao!B4:H4)) -> 2.2 | D4: =IF(A4="","","Aguardando histórico (mín. ~50-100 casos)") -> Aguardando histórico (mín. ~50-100 casos) | E4: =IF(A4="","",CONCATENATE("Prioridade: ",B4," (score ",TEXT(C4,"0.0"),"). Maior aderência com o perfil atual dessa cliente.")) -> Prioridade: Esteira (score 2,2). Maior aderência com o perfil atual dessa cliente.
A5: =IF(Pontuacao!A5="","",Pontuacao!A5) | B5: {=IFERROR(IF(A5="","",INDEX(Pontuacao!$B$1:$H$1,MATCH(MAX(Pontuacao!B5:H5),Pontuacao!B5:H5,0))),"")} | C5: =IF(A5="","",MAX(Pontuacao!B5:H5)) | D5: =IF(A5="","","Aguardando histórico (mín. ~50-100 casos)") | E5: =IF(A5="","",CONCATENATE("Prioridade: ",B5," (score ",TEXT(C5,"0.0"),"). Maior aderência com o perfil atual dessa cliente."))
A6: =IF(Pontuacao!A6="","",Pontuacao!A6) | B6: {=IFERROR(IF(A6="","",INDEX(Pontuacao!$B$1:$H$1,MATCH(MAX(Pontuacao!B6:H6),Pontuacao!B6:H6,0))),"")} | C6: =IF(A6="","",MAX(Pontuacao!B6:H6)) | D6: =IF(A6="","","Aguardando histórico (mín. ~50-100 casos)") | E6: =IF(A6="","",CONCATENATE("Prioridade: ",B6," (score ",TEXT(C6,"0.0"),"). Maior aderência com o perfil atual dessa cliente."))
A7: =IF(Pontuacao!A7="","",Pontuacao!A7) | B7: {=IFERROR(IF(A7="","",INDEX(Pontuacao!$B$1:$H$1,MATCH(MAX(Pontuacao!B7:H7),Pontuacao!B7:H7,0))),"")} | C7: =IF(A7="","",MAX(Pontuacao!B7:H7)) | D7: =IF(A7="","","Aguardando histórico (mín. ~50-100 casos)") | E7: =IF(A7="","",CONCATENATE("Prioridade: ",B7," (score ",TEXT(C7,"0.0"),"). Maior aderência com o perfil atual dessa cliente."))
A8: =IF(Pontuacao!A8="","",Pontuacao!A8) | B8: {=IFERROR(IF(A8="","",INDEX(Pontuacao!$B$1:$H$1,MATCH(MAX(Pontuacao!B8:H8),Pontuacao!B8:H8,0))),"")} | C8: =IF(A8="","",MAX(Pontuacao!B8:H8)) | D8: =IF(A8="","","Aguardando histórico (mín. ~50-100 casos)") | E8: =IF(A8="","",CONCATENATE("Prioridade: ",B8," (score ",TEXT(C8,"0.0"),"). Maior aderência com o perfil atual dessa cliente."))
A9: =IF(Pontuacao!A9="","",Pontuacao!A9) | B9: {=IFERROR(IF(A9="","",INDEX(Pontuacao!$B$1:$H$1,MATCH(MAX(Pontuacao!B9:H9),Pontuacao!B9:H9,0))),"")} | C9: =IF(A9="","",MAX(Pontuacao!B9:H9)) | D9: =IF(A9="","","Aguardando histórico (mín. ~50-100 casos)") | E9: =IF(A9="","",CONCATENATE("Prioridade: ",B9," (score ",TEXT(C9,"0.0"),"). Maior aderência com o perfil atual dessa cliente."))
A10: =IF(Pontuacao!A10="","",Pontuacao!A10) | B10: {=IFERROR(IF(A10="","",INDEX(Pontuacao!$B$1:$H$1,MATCH(MAX(Pontuacao!B10:H10),Pontuacao!B10:H10,0))),"")} | C10: =IF(A10="","",MAX(Pontuacao!B10:H10)) | D10: =IF(A10="","","Aguardando histórico (mín. ~50-100 casos)") | E10: =IF(A10="","",CONCATENATE("Prioridade: ",B10," (score ",TEXT(C10,"0.0"),"). Maior aderência com o perfil atual dessa cliente."))
A11: =IF(Pontuacao!A11="","",Pontuacao!A11) | B11: {=IFERROR(IF(A11="","",INDEX(Pontuacao!$B$1:$H$1,MATCH(MAX(Pontuacao!B11:H11),Pontuacao!B11:H11,0))),"")} | C11: =IF(A11="","",MAX(Pontuacao!B11:H11)) | D11: =IF(A11="","","Aguardando histórico (mín. ~50-100 casos)") | E11: =IF(A11="","",CONCATENATE("Prioridade: ",B11," (score ",TEXT(C11,"0.0"),"). Maior aderência com o perfil atual dessa cliente."))
A12: =IF(Pontuacao!A12="","",Pontuacao!A12) | B12: {=IFERROR(IF(A12="","",INDEX(Pontuacao!$B$1:$H$1,MATCH(MAX(Pontuacao!B12:H12),Pontuacao!B12:H12,0))),"")} | C12: =IF(A12="","",MAX(Pontuacao!B12:H12)) | D12: =IF(A12="","","Aguardando histórico (mín. ~50-100 casos)") | E12: =IF(A12="","",CONCATENATE("Prioridade: ",B12," (score ",TEXT(C12,"0.0"),"). Maior aderência com o perfil atual dessa cliente."))
A13: =IF(Pontuacao!A13="","",Pontuacao!A13) | B13: {=IFERROR(IF(A13="","",INDEX(Pontuacao!$B$1:$H$1,MATCH(MAX(Pontuacao!B13:H13),Pontuacao!B13:H13,0))),"")} | C13: =IF(A13="","",MAX(Pontuacao!B13:H13)) | D13: =IF(A13="","","Aguardando histórico (mín. ~50-100 casos)") | E13: =IF(A13="","",CONCATENATE("Prioridade: ",B13," (score ",TEXT(C13,"0.0"),"). Maior aderência com o perfil atual dessa cliente."))
... A500: =IF(Pontuacao!A500="","",Pontuacao!A500) | B500: {=IFERROR(IF(A500="","",INDEX(Pontuacao!$B$1:$H$1,MATCH(MAX(Pontuacao!B500:H500),Pontuacao!B500:H500,0))),"")} | C500: =IF(A500="","",MAX(Pontuacao!B500:H500)) | D500: =IF(A500="","","Aguardando histórico (mín. ~50-100 casos)") | E500: =IF(A500="","",CONCATENATE("Prioridade: ",B500," (score ",TEXT(C500,"0.0"),"). Maior aderência com o perfil atual dessa cliente."))
